main.py
app/__init__.py
app/__main__.py
app/command_info.py
app/find_best.py
app/neural_network.py
app/settings.py
app/tool.py
cmd_find-0.0.1.dist-info/LICENSE
cmd_find-0.0.1.dist-info/METADATA
cmd_find-0.0.1.dist-info/WHEEL
cmd_find-0.0.1.dist-info/entry_points.txt
cmd_find-0.0.1.dist-info/top_level.txt
cmd_find-0.0.1.dist-info/RECORD
