Metadata-Version: 2.1
Name: cmd-find
Version: 0.0.1
Summary: A CLI tool that finds Linux commands from their descriptions
Home-page: https://github.com/Ben-Edwards44/cmd-find
Author: Ben Edwards
License: MIT
Classifier: Programming Language :: Python :: 3.11
Classifier: Operating System :: OS Independent
Classifier: Environment :: Console
Requires-Python: >=3.8
License-File: LICENSE
Requires-Dist: numpy
Requires-Dist: sentence-transformers
